baseline_generator/__init__.py
baseline_generator/cli.py
baseline_generator/generator.py
baseline_generator-1.1.0.dist-info/METADATA
baseline_generator-1.1.0.dist-info/WHEEL
baseline_generator-1.1.0.dist-info/entry_points.txt
baseline_generator-1.1.0.dist-info/RECORD
