Metadata-Version: 2.3
Name: baseline-generator
Version: 1.1.0
Summary: A Python package for generating and managing JSON test baselines
License: MIT
Author: Alejandro
Author-email: alejandro@gonzalvo.com
Requires-Python: >=3.12,<4.0
Classifier: License :: OSI Approved :: MIT License
Classifier: Programming Language :: Python :: 3
Classifier: Programming Language :: Python :: 3.12
Classifier: Programming Language :: Python :: 3.13
